superflag/__init__.py
superflag/__main__.py
superflag/__version__.py
superflag/claude_hook.py
superflag/cli.py
superflag/install.py
superflag/prompts.py
superflag/server.py
superflag/flags.yaml
superflag-3.0.23.dist-info/METADATA
superflag-3.0.23.dist-info/WHEEL
superflag-3.0.23.dist-info/entry_points.txt
superflag-3.0.23.dist-info/licenses/LICENSE
superflag-3.0.23.dist-info/RECORD
