Metadata-Version: 2.4
Name: superflag
Version: 3.0.23
Summary: MCP-based contextual flag system for AI assistants
Author-email: Hyunjae Lim <thecurrent.lim@gmail.com>
License: MIT
License-File: LICENSE
Requires-Python: >=3.10
Requires-Dist: fastmcp<3.0.0,>=2.0.0
Requires-Dist: mcp[cli]>=1.0.0
Requires-Dist: psutil>=5.0.0
Requires-Dist: pyyaml>=6.0.0
